__init__.py
dasm.py
gasm.py
gasm-1.1.8.dist-info/LICENSE
gasm-1.1.8.dist-info/METADATA
gasm-1.1.8.dist-info/WHEEL
gasm-1.1.8.dist-info/entry_points.txt
gasm-1.1.8.dist-info/top_level.txt
gasm-1.1.8.dist-info/RECORD
