Metadata-Version: 2.1
Name: gasm
Version: 1.1.8
Summary: An assembler/dissassembler for the Gheith ISA
Author-email: Michael Goppert <goppert@cs.utexas.edu>
License: MIT License
Project-URL: Homepage, https://github.com/migopp/gasm
Classifier: Programming Language :: Python :: 3
Requires-Python: >=3.8
License-File: LICENSE
